duckargs/__init__.py
duckargs/__main__.py
duckargs/config.py
duckargs-1.5.1.dist-info/LICENSE
duckargs-1.5.1.dist-info/METADATA
duckargs-1.5.1.dist-info/WHEEL
duckargs-1.5.1.dist-info/entry_points.txt
duckargs-1.5.1.dist-info/top_level.txt
duckargs-1.5.1.dist-info/RECORD
