Metadata-Version: 2.1
Name: duckargs
Version: 1.5.1
Summary: Code generation tool, creates python / C programs that parse command line arguments. Say goodbye to starting each project by reading "argparse" / "geptopt.h" docs.
Home-page: http://github.com/eriknyquist/duckargs
Author: Erik Nyquist
Author-email: eknyquist@gmail.com
License: Apache 2.0
Project-URL: Documentation, https://github.com/eriknyquist/duckargs
Project-URL: Issues, https://github.com/eriknyquist/duckargs/issues
Project-URL: Contributions, https://github.com/eriknyquist/duckargs/pulls
Classifier: Development Status :: 5 - Production/Stable
Classifier: Intended Audience :: Developers
Classifier: Intended Audience :: Science/Research
Classifier: Intended Audience :: Education
Classifier: Intended Audience :: Information Technology
Classifier: License :: OSI Approved :: Apache Software License
Classifier: Programming Language :: Python :: 3
Classifier: Programming Language :: Python :: 3.7
Classifier: Programming Language :: Python :: 3.8
Classifier: Programming Language :: Python :: 3.9
Classifier: Programming Language :: Python :: 3.10
Requires-Python: >=3.7
License-File: LICENSE
